mkDOCter/__init__.py
mkDOCter/main.html
mkDOCter/css/main.css
mkDOCter/css/normalize.css
mkDOCter/css/syntax.css
mkDOCter/js/respond.min.js
mkDOCter-1.0.5.dist-info/DESCRIPTION.rst
mkDOCter-1.0.5.dist-info/METADATA
mkDOCter-1.0.5.dist-info/RECORD
mkDOCter-1.0.5.dist-info/WHEEL
mkDOCter-1.0.5.dist-info/entry_points.txt
mkDOCter-1.0.5.dist-info/metadata.json
mkDOCter-1.0.5.dist-info/pbr.json
mkDOCter-1.0.5.dist-info/top_level.txt
