Metadata-Version: 2.0
Name: mkDOCter
Version: 1.0.5
Summary: mkdocs theme based on DOCter
Home-page: https://github.com/willbarton/mkDOCter
Author: Will Barton
Author-email: william.barton@cfpb.gov
License: CC0
Platform: UNKNOWN
Classifier: License :: CC0 1.0 Universal (CC0 1.0) Public Domain Dedication
Classifier: License :: Public Domain
Classifier: Programming Language :: Python
Classifier: Programming Language :: Python :: 2
Classifier: Programming Language :: Python :: 2.7
Classifier: Programming Language :: Python :: 3
Classifier: Programming Language :: Python :: 3.6
